jill/.gnupg/juliareleases.asc
jill/__init__.py
jill/__main__.py
jill/config/alias.json
jill/config/placeholders.json
jill/config/sources.json
jill/config/versions-schema.json
jill/download.py
jill/install.py
jill/list.py
jill/switch.py
jill/utils/__init__.py
jill/utils/defaults.py
jill/utils/filters.py
jill/utils/gpg_utils.py
jill/utils/interactive_utils.py
jill/utils/mount_utils.py
jill/utils/net_utils.py
jill/utils/source_utils.py
jill/utils/sys_utils.py
jill/utils/version_utils.py
jill-0.12.0.dist-info/entry_points.txt
jill-0.12.0.dist-info/LICENSE
jill-0.12.0.dist-info/METADATA
jill-0.12.0.dist-info/WHEEL
jill-0.12.0.dist-info/RECORD
