Metadata-Version: 2.3
Name: jill
Version: 0.12.0
Summary: JILL -- Julia Installer for Linux (MacOS, Windows and FreeBSD) -- Light
License: MIT
Keywords: julia,installer
Author: johnnychen94
Author-email: johnnychen94@hotmail.com
Requires-Python: >=3.8,<4.0
Classifier: License :: OSI Approved :: MIT License
Classifier: Operating System :: OS Independent
Classifier: Programming Language :: Python :: 3
Classifier: Programming Language :: Python :: 3.8
Classifier: Programming Language :: Python :: 3.9
Classifier: Programming Language :: Python :: 3.10
Classifier: Programming Language :: Python :: 3.11
Classifier: Programming Language :: Python :: 3.12
Classifier: Programming Language :: Python :: 3.13
Requires-Dist: click (>=8.1.7,<9.0.0)
Requires-Dist: httpx (>=0.27,<0.28)
Requires-Dist: jsonschema (>=4.17.3,<5.0.0)
Requires-Dist: python-gnupg (>=0.5.0,<0.6.0)
Requires-Dist: semantic-version (>=2.10.0,<3.0.0)
Project-URL: Repository, https://github.com/johnnychen94/jill.py
